html_and_py/__init__.py
html_and_py/html_and_py.py
html_and_py-1.0.14.dist-info/LICENSE
html_and_py-1.0.14.dist-info/METADATA
html_and_py-1.0.14.dist-info/WHEEL
html_and_py-1.0.14.dist-info/top_level.txt
html_and_py-1.0.14.dist-info/RECORD
