Metadata-Version: 2.1
Name: html-and-py
Version: 1.0.14
Summary: A lightweight solution to generating HTML-formatted strings, in Python
Home-page: https://github.com/Whoeza/html_and_py
Author: Whoeza
License: GNU GPLv3
Project-URL: Bug Tracker, https://github.com/Whoeza/html_and_py/issues
Classifier: Intended Audience :: Developers
Classifier: License :: OSI Approved :: GNU General Public License v3 (GPLv3)
Classifier: Operating System :: OS Independent
Classifier: Programming Language :: ML
Classifier: Programming Language :: Python :: 3
Classifier: Topic :: Software Development :: Code Generators
Classifier: Topic :: Text Processing :: Markup :: HTML
Requires-Python: >=3.6
License-File: LICENSE
